sarathi/__init__.py
sarathi/cli/__init__.py
sarathi/cli/banner.py
sarathi/cli/chat_cli.py
sarathi/cli/cli_handler.py
sarathi/cli/code_cli.py
sarathi/cli/config_cli.py
sarathi/cli/gendocstrings.py
sarathi/cli/model_cli.py
sarathi/cli/registry.py
sarathi/cli/sbom_cli.py
sarathi/cli/sgit.py
sarathi/code/__init__.py
sarathi/code/code_agent.py
sarathi/code/codetasks.py
sarathi/config/config_manager.py
sarathi/llm/__init__.py
sarathi/llm/agent_engine.py
sarathi/llm/async_llm.py
sarathi/llm/call_llm.py
sarathi/llm/parallel_analyzer.py
sarathi/llm/tool_library.py
sarathi/llm/tools.py
sarathi/utils/formatters.py
sarathi/utils/io.py
sarathi/utils/usage.py
sarathi-0.0.5.dist-info/licenses/LICENSE
sarathi-0.0.5.dist-info/METADATA
sarathi-0.0.5.dist-info/WHEEL
sarathi-0.0.5.dist-info/entry_points.txt
sarathi-0.0.5.dist-info/top_level.txt
sarathi-0.0.5.dist-info/RECORD
