Metadata-Version: 2.4
Name: sarathi
Version: 0.0.5
Summary: A CLI coding assistant
Author: Abhishek Sharma
License: MIT
Project-URL: Bug Reports, https://github.com/abhishek9sharma/sarathi/issues
Project-URL: Source, https://github.com/abhishek9sharma/sarathi
Keywords: cli,coding assistant
Classifier: Development Status :: 3 - Alpha
Classifier: Intended Audience :: Developers
Classifier: Topic :: Software Development :: Build Tools
Classifier: License :: OSI Approved :: MIT License
Requires-Python: >=3.9
License-File: LICENSE
Requires-Dist: httpx
Requires-Dist: astor
Requires-Dist: black
Requires-Dist: PyYAML
Requires-Dist: aiohttp>=3.10.11
Requires-Dist: questionary
Requires-Dist: rich
Provides-Extra: test
Requires-Dist: pytest; extra == "test"
Requires-Dist: pytest-mock; extra == "test"
Requires-Dist: pytest-cov; extra == "test"
Provides-Extra: dev
Requires-Dist: sarathi[test]; extra == "dev"
Requires-Dist: twine>=4.0.2; extra == "dev"
Requires-Dist: wheel; extra == "dev"
Requires-Dist: black; extra == "dev"
Requires-Dist: isort; extra == "dev"
Dynamic: license-file
